README.md
setup.py
brave_history/__init__.py
brave_history/main.py
brave_history.egg-info/PKG-INFO
brave_history.egg-info/SOURCES.txt
brave_history.egg-info/dependency_links.txt
brave_history.egg-info/entry_points.txt
brave_history.egg-info/requires.txt
brave_history.egg-info/top_level.txt