Metadata-Version: 2.1
Name: brave-history
Version: 1.2.0
Summary: Search brave history from the command-line
Home-page: 
Author: @readwithai
Author-email: talwrii@gmail.com
License: BSD
Keywords: brave,history,cli,command-line
